open_spec_correct/__init__.py
open_spec_correct/main.py
open_spec_correct/prompts.py
open_spec_correct-2025.12.21155728.dist-info/METADATA
open_spec_correct-2025.12.21155728.dist-info/WHEEL
open_spec_correct-2025.12.21155728.dist-info/top_level.txt
open_spec_correct-2025.12.21155728.dist-info/RECORD
