Metadata-Version: 2.4
Name: open-spec-correct
Version: 2025.12.21155728
Summary: A new package designed to streamline and automate the correction of imperfect OpenAPI specifications by analyzing user-provided textual descriptions and extracting structured insights. It processes te
Author-email: open-spec-correct <hi@eugene.plus>
License: MIT
Project-URL: Homepage, https://github.com/chigwell/open-spec-correct
Requires-Python: >=3.9
Requires-Dist: langchain-llm7>=0.0.0
Requires-Dist: llmatch-messages>=0.0.0
Requires-Dist: langchain-core>=0.3.0
